{
 "custom_fields": [],
 "custom_perms": [],
 "doctype": "Attendance",
 "property_setters": [
  {
   "_assign": null,
   "_comments": null,
   "_liked_by": null,
   "_user_tags": null,
   "creation": "2022-05-22 02:19:08.216042",
   "default_value": null,
   "doc_type": "Attendance",
   "docstatus": 0,
   "doctype_or_field": "DocField",
   "field_name": "early_exit",
   "idx": 0,
   "modified": "2022-05-22 02:19:08.216042",
   "modified_by": "Administrator",
   "name": "Attendance-early_exit-description",
   "owner": "Administrator",
   "parent": null,
   "parentfield": null,
   "parenttype": null,
   "property": "description",
   "property_type": "Text",
   "row_name": null,
   "value": "\u064a\u0645\u0643\u0646\u0643 \u062a\u0641\u0639\u064a\u0644 \u0647\u0630\u0627 \u0627\u0644\u062e\u064a\u0627\u0631 \u0641\u064a \u062d\u0627\u0644\u0629 \u062e\u0631\u0648\u062c \u0627\u0644\u0645\u0648\u0638\u0641 \u0642\u0628\u0644 \u0645\u064a\u0639\u0627\u062f \u0627\u0646\u062a\u0647\u0627\u0621 \u0627\u0644\u0648\u0631\u062f\u064a\u0629"
  },
  {
   "_assign": null,
   "_comments": null,
   "_liked_by": null,
   "_user_tags": null,
   "creation": "2022-05-22 02:19:08.192112",
   "default_value": null,
   "doc_type": "Attendance",
   "docstatus": 0,
   "doctype_or_field": "DocField",
   "field_name": "late_entry",
   "idx": 0,
   "modified": "2022-05-22 02:19:08.192112",
   "modified_by": "Administrator",
   "name": "Attendance-late_entry-description",
   "owner": "Administrator",
   "parent": null,
   "parentfield": null,
   "parenttype": null,
   "property": "description",
   "property_type": "Text",
   "row_name": null,
   "value": "\u064a\u0645\u0643\u0646\u0643 \u062a\u0641\u0639\u064a\u0644 \u0647\u0630\u0627 \u0627\u0644\u062e\u064a\u0627\u0631 \u0641\u064a \u062d\u0627\u0644\u0629 \u0648\u0635\u0648\u0644 \u0627\u0644\u0645\u0648\u0638\u0641 \u0645\u062a\u0627\u062e\u0631\u0627"
  },
  {
   "_assign": null,
   "_comments": null,
   "_liked_by": null,
   "_user_tags": null,
   "creation": "2022-05-22 02:19:08.167588",
   "default_value": null,
   "doc_type": "Attendance",
   "docstatus": 0,
   "doctype_or_field": "DocField",
   "field_name": "shift",
   "idx": 0,
   "modified": "2022-05-22 02:19:08.167588",
   "modified_by": "Administrator",
   "name": "Attendance-shift-description",
   "owner": "Administrator",
   "parent": null,
   "parentfield": null,
   "parenttype": null,
   "property": "description",
   "property_type": "Text",
   "row_name": null,
   "value": "\u0642\u0645 \u0628\u062a\u062d\u062f\u064a\u062f \u0646\u0648\u0639 \u0627\u0644\u0648\u0631\u062f\u064a\u0629 \u0627\u0644\u062a\u064a \u064a\u0648\u062c\u062f \u0641\u064a\u0647\u0627 \u0627\u0644\u0645\u0648\u0638\u0641"
  },
  {
   "_assign": null,
   "_comments": null,
   "_liked_by": null,
   "_user_tags": null,
   "creation": "2022-05-22 02:19:08.143466",
   "default_value": null,
   "doc_type": "Attendance",
   "docstatus": 0,
   "doctype_or_field": "DocField",
   "field_name": "company",
   "idx": 0,
   "modified": "2022-05-22 02:19:08.143466",
   "modified_by": "Administrator",
   "name": "Attendance-company-description",
   "owner": "Administrator",
   "parent": null,
   "parentfield": null,
   "parenttype": null,
   "property": "description",
   "property_type": "Text",
   "row_name": null,
   "value": "\u064a\u062a\u064a\u062d \u0627\u0644\u0646\u0638\u0627\u0645 \u0627\u0646\u0634\u0627\u0621 \u0634\u0631\u0643\u0627\u062a \u0642\u0627\u0628\u0636\u0629 \u0648\u0634\u0631\u0643\u0627\u062a \u0634\u0642\u064a\u0642\u0629 \u0639\u0644\u0649 \u0646\u0641\u0633 \u0627\u0644\u0628\u0631\u0646\u0627\u0645\u062c . \u0644\u0630\u0649 \u064a\u0645\u0643\u0646\u0643 \u0627\u062e\u062a\u064a\u0627\u0631 \u0627\u0644\u0634\u0631\u0643\u0629 \u0627\u0644\u062e\u0627\u0635\u0629 \u0628\u0627\u0644\u0645\u0648\u0638\u0641"
  },
  {
   "_assign": null,
   "_comments": null,
   "_liked_by": null,
   "_user_tags": null,
   "creation": "2022-05-22 02:19:08.118602",
   "default_value": null,
   "doc_type": "Attendance",
   "docstatus": 0,
   "doctype_or_field": "DocField",
   "field_name": "attendance_date",
   "idx": 0,
   "modified": "2022-05-22 02:19:08.118602",
   "modified_by": "Administrator",
   "name": "Attendance-attendance_date-description",
   "owner": "Administrator",
   "parent": null,
   "parentfield": null,
   "parenttype": null,
   "property": "description",
   "property_type": "Text",
   "row_name": null,
   "value": "\u0642\u0645 \u0628\u0627\u062e\u062a\u064a\u0627\u0631 \u062a\u0627\u0631\u064a\u062e \u062d\u0636\u0648\u0631 \u0627\u0644\u0645\u0648\u0638\u0641"
  },
  {
   "_assign": null,
   "_comments": null,
   "_liked_by": null,
   "_user_tags": null,
   "creation": "2022-05-22 02:19:08.092970",
   "default_value": null,
   "doc_type": "Attendance",
   "docstatus": 0,
   "doctype_or_field": "DocField",
   "field_name": "status",
   "idx": 0,
   "modified": "2022-05-22 02:19:08.092970",
   "modified_by": "Administrator",
   "name": "Attendance-status-description",
   "owner": "Administrator",
   "parent": null,
   "parentfield": null,
   "parenttype": null,
   "property": "description",
   "property_type": "Text",
   "row_name": null,
   "value": "\u0642\u0645 \u0628\u0627\u062e\u062a\u064a\u0627\u0631 \u062d\u0627\u0644\u0629 \u0627\u0644\u0645\u0648\u0638\u0641 \u0633\u0648\u0627\u0621 \u0643\u0627\u0646 (\u062d\u0627\u0636\u0631\u0627 \u0627\u0648 \u063a\u0627\u0626\u0628 \u0627\u0648 \u0641\u064a \u0627\u062c\u0627\u0632\u0629 \u0627\u0648 \u064a\u0639\u0645\u0644 \u0645\u0646 \u0627\u0644\u0645\u0646\u0632\u0644 )"
  },
  {
   "_assign": null,
   "_comments": null,
   "_liked_by": null,
   "_user_tags": null,
   "creation": "2022-05-22 02:19:08.041776",
   "default_value": null,
   "doc_type": "Attendance",
   "docstatus": 0,
   "doctype_or_field": "DocField",
   "field_name": "employee",
   "idx": 0,
   "modified": "2022-05-22 02:19:08.041776",
   "modified_by": "Administrator",
   "name": "Attendance-employee-description",
   "owner": "Administrator",
   "parent": null,
   "parentfield": null,
   "parenttype": null,
   "property": "description",
   "property_type": "Text",
   "row_name": null,
   "value": "\u0642\u0645 \u0628\u0627\u062f\u062e\u0627\u0644 \u0627\u0633\u0645 \u0627\u0648 \u0631\u0642\u0645 \u0627\u0644\u0645\u0648\u0638\u0641 \u0627\u0644\u0630\u064a \u062a\u0631\u064a\u062f \u062a\u0633\u062c\u064a\u0644 \u062d\u0636\u0648\u0631\u0647"
  },
  {
   "_assign": null,
   "_comments": null,
   "_liked_by": null,
   "_user_tags": null,
   "creation": "2022-05-22 01:25:46.622278",
   "default_value": null,
   "doc_type": "Attendance",
   "docstatus": 0,
   "doctype_or_field": "DocField",
   "field_name": "naming_series",
   "idx": 0,
   "modified": "2022-05-22 01:25:46.622278",
   "modified_by": "Administrator",
   "name": "Attendance-naming_series-description",
   "owner": "Administrator",
   "parent": null,
   "parentfield": null,
   "parenttype": null,
   "property": "description",
   "property_type": "Text",
   "row_name": null,
   "value": "\u064a\u0645\u0643\u0646\u0643 \u0627\u062e\u062a\u064a\u0627\u0631 \u0631\u0642\u0645 \u0645\u0633\u0644\u0633\u0644 \u062e\u0627\u0635 \u0628\u0627\u0644\u062d\u0636\u0648\u0631 \u062d\u064a\u062b \u064a\u0643\u0648\u0646 \u0644\u0643\u0644 \u0645\u0648\u0638\u0641 \u0627\u0643\u062b\u0631 \u0645\u0646 \u0631\u0642\u0645 \u0645\u0633\u0644\u0633\u0644 \u0644\u0644\u062d\u0636\u0648\u0631"
  }
 ],
 "sync_on_migrate": 1
}